conversor_de_unidades/__init__.py
conversor_de_unidades/temperatura.py
tests/__init__.py
tests/test_temperatura.py
conversor_de_unidades-0.0.1.dist-info/METADATA
conversor_de_unidades-0.0.1.dist-info/WHEEL
conversor_de_unidades-0.0.1.dist-info/top_level.txt
conversor_de_unidades-0.0.1.dist-info/RECORD
