Metadata-Version: 2.1
Name: conversor_de_unidades
Version: 0.0.1
Summary: Converte direntes unidades
Home-page: https://github.com/DavidSilveira80/simple-package-template
Author: DavidSilveira80
Author-email: davidpsdeveloper80@gmail.com
License: UNKNOWN
Platform: UNKNOWN
Requires-Python: >=3.9
